auto_keyword_ranker-0.1.10.dist-info/licenses/LICENSE
autokeyword/__init__.py
autokeyword/cli.py
autokeyword/core.py
auto_keyword_ranker-0.1.10.dist-info/METADATA
auto_keyword_ranker-0.1.10.dist-info/WHEEL
auto_keyword_ranker-0.1.10.dist-info/entry_points.txt
auto_keyword_ranker-0.1.10.dist-info/top_level.txt
auto_keyword_ranker-0.1.10.dist-info/RECORD
