Metadata-Version: 2.4
Name: auto-keyword-ranker
Version: 0.1.10
Summary: Lightweight keyword & keyphrase extraction and ranking using TF-IDF with optional embedding re-ranking.
Author-email: Reya Oberoi <reyaoberoi2005@gmail.com>
License: MIT
Project-URL: Homepage, https://github.com/reyaoberoi/auto-keyword-ranker
Project-URL: Repository, https://github.com/reyaoberoi/auto-keyword-ranker
Project-URL: Bug Tracker, https://github.com/reyaoberoi/auto-keyword-ranker/issues
Keywords: nlp,keywords,tfidf,embeddings,text
Classifier: Programming Language :: Python :: 3
Classifier: License :: OSI Approved :: MIT License
Classifier: Operating System :: OS Independent
Requires-Python: >=3.8
License-File: LICENSE
Requires-Dist: numpy>=1.21
Requires-Dist: scikit-learn>=1.0
Provides-Extra: embed
Requires-Dist: sentence-transformers>=2.2; extra == "embed"
Provides-Extra: dev
Requires-Dist: pytest; extra == "dev"
Requires-Dist: build; extra == "dev"
Requires-Dist: twine; extra == "dev"
Dynamic: license-file
